qlink_interface/__init__.py
qlink_interface/interface.py
qlink_interface-1.0.0.dist-info/LICENSE
qlink_interface-1.0.0.dist-info/METADATA
qlink_interface-1.0.0.dist-info/WHEEL
qlink_interface-1.0.0.dist-info/top_level.txt
qlink_interface-1.0.0.dist-info/RECORD
