Metadata-Version: 2.1
Name: qlink-interface
Version: 1.0.0
Summary: Interface definition of link layer for quantum networks
Home-page: https://github.com/SoftwareQuTech/QLink-Interface
Author: Axel Dahlberg
Author-email: e.a.dahlberg@tudelft.nl
License: MIT
Platform: UNKNOWN
Requires-Python: >=3.6
